mab_lite_dhruv/__init__.py
mab_lite_dhruv/multiarmbandit.py
mab_lite_dhruv-0.1.2.dist-info/METADATA
mab_lite_dhruv-0.1.2.dist-info/WHEEL
mab_lite_dhruv-0.1.2.dist-info/licenses/LICENSE
mab_lite_dhruv-0.1.2.dist-info/RECORD
