Metadata-Version: 2.4
Name: mab-lite-dhruv
Version: 0.1.2
Summary: Minimal multi-armed bandit helpers: pure exploration & pure exploitation.
Project-URL: Homepage, https://github.com/dhruvpithadia/mab-lite-dhruv
Project-URL: Issues, https://github.com/dhruvpithadia/mab-lite-dhruv/issues
Author: Dhruv Pithadia
License: MIT
License-File: LICENSE
Keywords: bandit,exploitation,exploration,multi-armed-bandit,reinforcement-learning
Classifier: Intended Audience :: Science/Research
Classifier: License :: OSI Approved :: MIT License
Classifier: Programming Language :: Python :: 3
Classifier: Topic :: Scientific/Engineering :: Artificial Intelligence
Requires-Python: >=3.8
